trio_cdp/__init__.py
trio_cdp/context.py
trio_cdp/generated/__init__.py
trio_cdp/generated/accessibility.py
trio_cdp/generated/animation.py
trio_cdp/generated/application_cache.py
trio_cdp/generated/audits.py
trio_cdp/generated/background_service.py
trio_cdp/generated/browser.py
trio_cdp/generated/cache_storage.py
trio_cdp/generated/cast.py
trio_cdp/generated/console.py
trio_cdp/generated/css.py
trio_cdp/generated/database.py
trio_cdp/generated/debugger.py
trio_cdp/generated/device_orientation.py
trio_cdp/generated/dom.py
trio_cdp/generated/dom_debugger.py
trio_cdp/generated/dom_snapshot.py
trio_cdp/generated/dom_storage.py
trio_cdp/generated/emulation.py
trio_cdp/generated/fetch.py
trio_cdp/generated/headless_experimental.py
trio_cdp/generated/heap_profiler.py
trio_cdp/generated/indexed_db.py
trio_cdp/generated/input_.py
trio_cdp/generated/inspector.py
trio_cdp/generated/io.py
trio_cdp/generated/layer_tree.py
trio_cdp/generated/log.py
trio_cdp/generated/memory.py
trio_cdp/generated/network.py
trio_cdp/generated/overlay.py
trio_cdp/generated/page.py
trio_cdp/generated/performance.py
trio_cdp/generated/profiler.py
trio_cdp/generated/runtime.py
trio_cdp/generated/schema.py
trio_cdp/generated/security.py
trio_cdp/generated/service_worker.py
trio_cdp/generated/storage.py
trio_cdp/generated/system_info.py
trio_cdp/generated/target.py
trio_cdp/generated/tethering.py
trio_cdp/generated/tracing.py
trio_cdp/generated/web_audio.py
trio_cdp/generated/web_authn.py
trio_cdp/py.typed
trio_chrome_devtools_protocol-0.6.0.dist-info/LICENSE
trio_chrome_devtools_protocol-0.6.0.dist-info/WHEEL
trio_chrome_devtools_protocol-0.6.0.dist-info/METADATA
trio_chrome_devtools_protocol-0.6.0.dist-info/RECORD
