Metadata-Version: 2.1
Name: trio-chrome-devtools-protocol
Version: 0.6.0
Summary: Trio driver for Chrome DevTools Protocol (CDP)
Home-page: https://github.com/hyperiongray/python-chrome-devtools-protocol
License: MIT
Author: Mark E. Haase
Author-email: mehaase@gmail.com
Requires-Python: >=3.7,<4.0
Classifier: Development Status :: 3 - Alpha
Classifier: Intended Audience :: Developers
Classifier: License :: OSI Approved :: MIT License
Classifier: Programming Language :: Python :: 3
Classifier: Programming Language :: Python :: 3.7
Classifier: Programming Language :: Python :: 3.8
Classifier: Topic :: Internet
Requires-Dist: chrome-devtools-protocol (>=0.3.0,<0.4.0)
Requires-Dist: trio (>=0.13.0,<0.14.0)
Requires-Dist: trio_websocket (>=0.8.0,<0.9.0)
